{
  "version": "5",
  "dialect": "pg",
  "id": "75b584cd-75cd-49fc-ba18-eaeeaf22f556",
  "prevId": "b2f8ed42-db2c-4f0f-8ca3-dda47b6fecf6",
  "tables": {
    "orders": {
      "name": "orders",
      "schema": "",
      "columns": {
        "id": {
          "name": "id",
          "type": "serial",
          "primaryKey": true,
          "notNull": true
        },
        "orderId": {
          "name": "orderId",
          "type": "varchar",
          "primaryKey": false,
          "notNull": false
        },
        "customer_name": {
          "name": "customer_name",
          "type": "varchar(256)",
          "primaryKey": false,
          "notNull": false
        },
        "supplier_name": {
          "name": "supplier_name",
          "type": "varchar(256)",
          "primaryKey": false,
          "notNull": false
        },
        "created_at": {
          "name": "created_at",
          "type": "timestamp with time zone",
          "primaryKey": false,
          "notNull": false
        }
      },
      "indexes": {},
      "foreignKeys": {},
      "compositePrimaryKeys": {},
      "uniqueConstraints": {
        "orders_orderId_unique": {
          "name": "orders_orderId_unique",
          "nullsNotDistinct": false,
          "columns": [
            "orderId"
          ]
        }
      }
    },
    "orders_products": {
      "name": "orders_products",
      "schema": "",
      "columns": {
        "id": {
          "name": "id",
          "type": "serial",
          "primaryKey": true,
          "notNull": true
        },
        "order_id": {
          "name": "order_id",
          "type": "integer",
          "primaryKey": false,
          "notNull": false
        },
        "product_id": {
          "name": "product_id",
          "type": "integer",
          "primaryKey": false,
          "notNull": false
        },
        "supplier_name": {
          "name": "supplier_name",
          "type": "varchar(256)",
          "primaryKey": false,
          "notNull": false
        }
      },
      "indexes": {},
      "foreignKeys": {
        "orders_products_order_id_orders_id_fk": {
          "name": "orders_products_order_id_orders_id_fk",
          "tableFrom": "orders_products",
          "tableTo": "orders",
          "columnsFrom": [
            "order_id"
          ],
          "columnsTo": [
            "id"
          ],
          "onDelete": "no action",
          "onUpdate": "no action"
        },
        "orders_products_product_id_products_id_fk": {
          "name": "orders_products_product_id_products_id_fk",
          "tableFrom": "orders_products",
          "tableTo": "products",
          "columnsFrom": [
            "product_id"
          ],
          "columnsTo": [
            "id"
          ],
          "onDelete": "no action",
          "onUpdate": "no action"
        }
      },
      "compositePrimaryKeys": {},
      "uniqueConstraints": {}
    },
    "products": {
      "name": "products",
      "schema": "",
      "columns": {
        "id": {
          "name": "id",
          "type": "serial",
          "primaryKey": true,
          "notNull": true
        },
        "product_name": {
          "name": "product_name",
          "type": "varchar(256)",
          "primaryKey": false,
          "notNull": false
        }
      },
      "indexes": {},
      "foreignKeys": {},
      "compositePrimaryKeys": {},
      "uniqueConstraints": {}
    },
    "recipes": {
      "name": "recipes",
      "schema": "",
      "columns": {
        "id": {
          "name": "id",
          "type": "serial",
          "primaryKey": true,
          "notNull": true
        },
        "product_name": {
          "name": "product_name",
          "type": "varchar(256)",
          "primaryKey": false,
          "notNull": false
        }
      },
      "indexes": {},
      "foreignKeys": {},
      "compositePrimaryKeys": {},
      "uniqueConstraints": {}
    }
  },
  "enums": {},
  "schemas": {},
  "_meta": {
    "schemas": {},
    "tables": {},
    "columns": {}
  }
}